github_username_validator/__init__.py
github_username_validator-0.1.0.dist-info/METADATA
github_username_validator-0.1.0.dist-info/WHEEL
github_username_validator-0.1.0.dist-info/top_level.txt
github_username_validator-0.1.0.dist-info/RECORD
