Metadata-Version: 2.1
Name: github_username_validator
Version: 0.1.0
Summary: Library untuk validasi username GitHub
Home-page: https://github.com/imnoob59/github_username_validator
Author: su21
Author-email: santounyil21041998@gmail.com
Classifier: Programming Language :: Python :: 3
Classifier: License :: OSI Approved :: MIT License
Classifier: Operating System :: OS Independent
Requires-Python: >=3.6
Requires-Dist: requests
